alfacoins
tests
